pcidevlib/__init__.py
pcidevlib-0.1.dev4.dist-info/LICENSE
pcidevlib-0.1.dev4.dist-info/METADATA
pcidevlib-0.1.dev4.dist-info/WHEEL
pcidevlib-0.1.dev4.dist-info/top_level.txt
pcidevlib-0.1.dev4.dist-info/RECORD
