Metadata-Version: 2.1
Name: pcidevlib
Version: 0.1.dev4
Summary: Custom PCI device utils for reading writing.
Home-page: https://github.com/as43z/pci-dev-lib
Author: Albert Sáez Núñez
Project-URL: Source Code, https://github.com/as43z/pci-dev-lib
Keywords: setuptools,pci,device,mmio,memory
Classifier: Development Status :: 2 - Pre-Alpha
Classifier: Programming Language :: Python :: 3 :: Only
Classifier: Programming Language :: Python :: 3.9
Classifier: Programming Language :: Python :: 3.10
Classifier: License :: OSI Approved :: MIT License
Requires-Python: >=3.7, <4
License-File: LICENSE
